.gitignore
CHANGELOG.rst
MANIFEST.in
pyproject.toml
requirements-dev.in
requirements.in
requirements.txt
setup.py
tox.ini
.circleci/config.yml
demo/run.py
demo/setup.py
demo/gw_utils_demo_app/__init__.py
demo/gw_utils_demo_app/__main__.py
demo/gw_utils_demo_app/app.py
demo/gw_utils_demo_app/tasks.py
demo/gw_utils_demo_app/transform.py
girder_worker_utils/__init__.py
girder_worker_utils/decorators.py
girder_worker_utils/tee.py
girder_worker_utils/transform.py
girder_worker_utils.egg-info/PKG-INFO
girder_worker_utils.egg-info/SOURCES.txt
girder_worker_utils.egg-info/dependency_links.txt
girder_worker_utils.egg-info/not-zip-safe
girder_worker_utils.egg-info/requires.txt
girder_worker_utils.egg-info/top_level.txt
girder_worker_utils/tests/__init__.py
girder_worker_utils/tests/decorators_test.py
girder_worker_utils/tests/girder_io_test.py
girder_worker_utils/tests/tee_test.py
girder_worker_utils/tests/transform_test.py
girder_worker_utils/tests/types_test.py
girder_worker_utils/tests/contrib/__init__.py
girder_worker_utils/tests/contrib/girder_io_test.py
girder_worker_utils/tests/fake_dir/file1.txt
girder_worker_utils/tests/fake_dir/file2.txt
girder_worker_utils/tests/fake_dir/subdir/file3.txt
girder_worker_utils/transforms/__init__.py
girder_worker_utils/transforms/common.py
girder_worker_utils/transforms/girder_io.py
girder_worker_utils/transforms/contrib/__init__.py
girder_worker_utils/transforms/contrib/girder_io.py
girder_worker_utils/types/__init__.py
girder_worker_utils/types/base.py
girder_worker_utils/types/boolean.py
girder_worker_utils/types/choice.py
girder_worker_utils/types/color.py
girder_worker_utils/types/girder.py
girder_worker_utils/types/girder_folder.py
girder_worker_utils/types/girder_item.py
girder_worker_utils/types/integer.py
girder_worker_utils/types/number.py
girder_worker_utils/types/number_choice.py
girder_worker_utils/types/number_multichoice.py
girder_worker_utils/types/number_vector.py
girder_worker_utils/types/range.py
girder_worker_utils/types/string.py
girder_worker_utils/types/string_choice.py
girder_worker_utils/types/string_multichoice.py
girder_worker_utils/types/string_vector.py
girder_worker_utils/types/vector.py