Metadata-Version: 2.1
Name: girder-worker-utils
Version: 0.9.5
Summary: Helper utilities for the Girder Worker
Author: Kitware, Inc.
Author-email: kitware@kitware.com
License: Apache 2.0
Classifier: Development Status :: 5 - Production/Stable
Classifier: License :: OSI Approved :: Apache Software License
Classifier: Operating System :: OS Independent
Classifier: Programming Language :: Python
Classifier: Programming Language :: Python :: 3
Classifier: Programming Language :: Python :: 3.8
Classifier: Programming Language :: Python :: 3.9
Classifier: Programming Language :: Python :: 3.10
Classifier: Programming Language :: Python :: 3.11
Classifier: Programming Language :: Python :: 3.12
Classifier: Programming Language :: Python :: 3.13
Requires-Python: >=3.8
Requires-Dist: girder-client>=2
Requires-Dist: jsonpickle
Requires-Dist: requests>=2.20.0
Requires-Dist: setuptools_scm
Requires-Dist: urllib3>=1.24.2
